cvdpack/__init__.py
cvdpack/checkdiff.py
cvdpack/main.py
cvdpack/pack_frames.py
cvdpack/pack_timeseries.py
cvdpack/util.py
cvdpack/presets/infinigen_2023_10_13_preview.json
cvdpack/presets/tartanair_floatingpoint.json
cvdpack/presets/tartanair_quantized.json
cvdpack-0.0.4.dist-info/METADATA
cvdpack-0.0.4.dist-info/WHEEL
cvdpack-0.0.4.dist-info/entry_points.txt
cvdpack-0.0.4.dist-info/licenses/LICENSE
cvdpack-0.0.4.dist-info/RECORD
