Metadata-Version: 2.4
Name: cvdpack
Version: 0.0.4
Summary: Quantize and video-compress your RGB/Depth/Flow/SurfaceNormal datasets
Author-email: Alexander Raistrick <araistrick@princeton.edu>
License: BSD-3-Clause
License-File: LICENSE
Keywords: computer vision,datasets
Classifier: Programming Language :: Python :: 3
Requires-Python: >3.10.0
Requires-Dist: numpy<2
Requires-Dist: opencv-python
Requires-Dist: tqdm
Provides-Extra: dev
Requires-Dist: matplotlib; extra == 'dev'
Requires-Dist: pytest; extra == 'dev'
Requires-Dist: ruff; extra == 'dev'
Provides-Extra: slurm
Requires-Dist: submitit; extra == 'slurm'
